checksumdir/__init__.py
checksumdir/__init__.pyi
checksumdir/cli.py
checksumdir/cli.pyi
checksumdir/py.typed
checksumdir-1.3.0.dist-info/LICENSE.txt
checksumdir-1.3.0.dist-info/METADATA
checksumdir-1.3.0.dist-info/WHEEL
checksumdir-1.3.0.dist-info/entry_points.txt
checksumdir-1.3.0.dist-info/RECORD
