Metadata-Version: 2.3
Name: checksumdir
Version: 1.3.0
Summary: Compute a single hash of the file contents of a directory.
License: MIT
Keywords: hash,checksum,md5,directory
Author: Tom McCarthy
Author-email: tmac.se@gmail.com
Requires-Python: >=3.9,<4.0
Classifier: License :: OSI Approved :: MIT License
Classifier: Operating System :: OS Independent
Classifier: Programming Language :: Python
Classifier: Programming Language :: Python :: 3
Classifier: Programming Language :: Python :: 3.9
Classifier: Programming Language :: Python :: 3.10
Classifier: Programming Language :: Python :: 3.11
Classifier: Programming Language :: Python :: 3.12
Classifier: Programming Language :: Python :: 3.13
Classifier: Topic :: Utilities
Project-URL: Homepage, http://github.com/cakepietoast/checksumdir
